pytest_ignore_test_results/__init__.py
pytest_ignore_test_results/hooks.py
pytest_ignore_test_results/ignore_results.py
pytest_ignore_test_results/plugin.py
pytest_ignore_test_results/utils.py
pytest_ignore_test_results-0.3.0.dist-info/entry_points.txt
pytest_ignore_test_results-0.3.0.dist-info/LICENSE
pytest_ignore_test_results-0.3.0.dist-info/WHEEL
pytest_ignore_test_results-0.3.0.dist-info/METADATA
pytest_ignore_test_results-0.3.0.dist-info/RECORD
