Metadata-Version: 2.3
Name: pytest-ignore-test-results
Version: 0.3.0
Summary: A pytest plugin to ignore test results.
Author-email: Fu Hanxi <fuhanxi@espressif.com>
Requires-Python: >=3.7
Classifier: License :: OSI Approved :: Apache Software License
Classifier: Framework :: Pytest
Classifier: Development Status :: 5 - Production/Stable
Classifier: Programming Language :: Python :: 3
Classifier: Programming Language :: Python :: 3.7
Classifier: Programming Language :: Python :: 3.8
Classifier: Programming Language :: Python :: 3.9
Classifier: Programming Language :: Python :: 3.10
Classifier: Programming Language :: Python :: 3.11
Classifier: Programming Language :: Python :: 3.12
Classifier: Programming Language :: Python :: 3.13
Requires-Dist: pytest>=7.0
Requires-Dist: sphinx ; extra == "doc"
Requires-Dist: sphinx-rtd-theme ; extra == "doc"
Requires-Dist: sphinx_copybutton ; extra == "doc"
Requires-Dist: myst-parser ; extra == "doc"
Requires-Dist: sphinxcontrib-mermaid ; extra == "doc"
Requires-Dist: pytest-cov ; extra == "test"
Project-URL: Changelog, https://github.com/espressif/pytest-ignore-test-results/blob/main/CHANGELOG.md
Project-URL: Homepage, https://github.com/espressif/pytest-ignore-test-results
Project-URL: Repository, https://github.com/espressif/pytest-ignore-test-results.git
Provides-Extra: doc
Provides-Extra: test
